pyrestr/__init__.py
pyrestr/dict_utils.py
pyrestr/num_utils.py
pyrestr/str_utils.py
pyrestr-0.1.0.dist-info/METADATA
pyrestr-0.1.0.dist-info/WHEEL
pyrestr-0.1.0.dist-info/top_level.txt
pyrestr-0.1.0.dist-info/RECORD
