Metadata-Version: 2.4
Name: pyrestr
Version: 0.1.0
Summary: A small Python library for dictionary utilities
Author-email: Yan <teivral3@gmail.com>
Requires-Python: >=3.8
